Metadata-Version: 2.1
Name: pyChatteringy
Version: 0.0.5a0
Summary: Create very simple, minimalistic Python 3 chatbots by using JSON
Home-page: https://github.com/CWKevo/pyChatteringy
Author: Kevo
Author-email: me@kevo.link
License: GPLv3
Keywords: python,python3,chatbot,bot,framework,ai,json,intents,conversation
Platform: UNKNOWN
Classifier: Development Status :: 3 - Alpha
Classifier: Intended Audience :: Developers
Classifier: Topic :: Software Development :: Build Tools
Classifier: License :: OSI Approved :: GNU General Public License v3 (GPLv3)
Classifier: Programming Language :: Python :: 3.6
Classifier: Programming Language :: Python :: 3.7
Classifier: Programming Language :: Python :: 3.8
Classifier: Programming Language :: Python :: 3.9
Requires-Dist: fuzzywuzzy
